{
  "_meta": {
    "description": "Production failure patterns: cascading failures, circuit breakers, retry storms",
    "scenario": "Simulates a database outage cascading through the service mesh",
    "incident_duration_minutes": 15,
    "traces": 60
  },
  "traces": [
    {
      "trace_id": "fail-0001-normal-before",
      "service.name": "api-gateway",
      "http.method": "GET",
      "http.route": "/api/v2/orders/:id",
      "http.status_code": 200,
      "duration_ms": 45,
      "span_count": 6,
      "error": false,
      "incident.phase": "pre-incident",
      "timestamp_offset_seconds": -300
    },
    {
      "trace_id": "fail-0002-db-slow-start",
      "service.name": "order-service",
      "db.system": "postgresql",
      "db.operation": "SELECT",
      "http.status_code": 200,
      "duration_ms": 2500,
      "span_count": 3,
      "error": false,
      "incident.phase": "degradation-start",
      "db.connection_pool.active": 18,
      "db.connection_pool.max": 20,
      "db.connection_pool.waiting": 5,
      "timestamp_offset_seconds": 0
    },
    {
      "trace_id": "fail-0003-db-pool-exhausted",
      "service.name": "order-service",
      "db.system": "postgresql",
      "db.operation": "SELECT",
      "http.status_code": 503,
      "duration_ms": 30000,
      "span_count": 2,
      "error": true,
      "error.message": "Connection pool exhausted: timeout waiting for connection",
      "incident.phase": "pool-exhaustion",
      "db.connection_pool.active": 20,
      "db.connection_pool.max": 20,
      "db.connection_pool.waiting": 45,
      "db.connection_pool.timeout_ms": 30000,
      "timestamp_offset_seconds": 30
    },
    {
      "trace_id": "fail-0004-upstream-timeout",
      "service.name": "api-gateway",
      "http.method": "GET",
      "http.route": "/api/v2/orders/:id",
      "http.status_code": 504,
      "duration_ms": 30050,
      "span_count": 4,
      "error": true,
      "error.message": "Gateway timeout: order-service did not respond",
      "incident.phase": "cascade-start",
      "downstream.service": "order-service",
      "downstream.status": 503,
      "timestamp_offset_seconds": 35
    },
    {
      "trace_id": "fail-0005-retry-attempt-1",
      "service.name": "checkout-service",
      "http.method": "GET",
      "http.route": "/internal/orders/:id",
      "http.status_code": 504,
      "duration_ms": 30100,
      "span_count": 5,
      "error": true,
      "error.message": "Upstream timeout on retry attempt 1",
      "incident.phase": "retry-storm",
      "retry.attempt": 1,
      "retry.max_attempts": 3,
      "retry.backoff_ms": 100,
      "timestamp_offset_seconds": 40
    },
    {
      "trace_id": "fail-0006-retry-attempt-2",
      "service.name": "checkout-service",
      "http.method": "GET",
      "http.route": "/internal/orders/:id",
      "http.status_code": 504,
      "duration_ms": 30200,
      "span_count": 5,
      "error": true,
      "error.message": "Upstream timeout on retry attempt 2",
      "incident.phase": "retry-storm",
      "retry.attempt": 2,
      "retry.max_attempts": 3,
      "retry.backoff_ms": 200,
      "timestamp_offset_seconds": 70
    },
    {
      "trace_id": "fail-0007-retry-attempt-3",
      "service.name": "checkout-service",
      "http.method": "GET",
      "http.route": "/internal/orders/:id",
      "http.status_code": 504,
      "duration_ms": 30400,
      "span_count": 5,
      "error": true,
      "error.message": "Upstream timeout on retry attempt 3 (final)",
      "incident.phase": "retry-storm",
      "retry.attempt": 3,
      "retry.max_attempts": 3,
      "retry.backoff_ms": 400,
      "retry.exhausted": true,
      "timestamp_offset_seconds": 100
    },
    {
      "trace_id": "fail-0008-circuit-trip",
      "service.name": "api-gateway",
      "http.method": "GET",
      "http.route": "/api/v2/orders/:id",
      "http.status_code": 503,
      "duration_ms": 5,
      "span_count": 2,
      "error": true,
      "error.message": "Circuit breaker OPEN for order-service",
      "incident.phase": "circuit-open",
      "circuit_breaker.name": "order-service-cb",
      "circuit_breaker.state": "open",
      "circuit_breaker.failure_count": 25,
      "circuit_breaker.failure_threshold": 20,
      "circuit_breaker.open_duration_seconds": 30,
      "timestamp_offset_seconds": 120
    },
    {
      "trace_id": "fail-0009-circuit-fast-fail",
      "service.name": "api-gateway",
      "http.method": "GET",
      "http.route": "/api/v2/orders/:id",
      "http.status_code": 503,
      "duration_ms": 2,
      "span_count": 2,
      "error": true,
      "error.message": "Circuit breaker OPEN - fast failing",
      "incident.phase": "circuit-open",
      "circuit_breaker.state": "open",
      "circuit_breaker.requests_rejected": 156,
      "timestamp_offset_seconds": 125
    },
    {
      "trace_id": "fail-0010-cascade-to-checkout",
      "service.name": "checkout-service",
      "http.method": "POST",
      "http.route": "/api/v2/checkout",
      "http.status_code": 503,
      "duration_ms": 45,
      "span_count": 8,
      "error": true,
      "error.message": "Cannot complete checkout: order-service unavailable",
      "incident.phase": "cascade-propagation",
      "affected_dependency": "order-service",
      "degraded_services": ["checkout-service", "order-service"],
      "timestamp_offset_seconds": 130
    },
    {
      "trace_id": "fail-0011-cascade-to-payment",
      "service.name": "payment-service",
      "http.method": "POST",
      "http.route": "/internal/refund",
      "http.status_code": 503,
      "duration_ms": 67,
      "span_count": 6,
      "error": true,
      "error.message": "Cannot process refund: order lookup failed",
      "incident.phase": "cascade-propagation",
      "affected_dependency": "order-service",
      "degraded_services": ["payment-service", "checkout-service", "order-service"],
      "timestamp_offset_seconds": 135
    },
    {
      "trace_id": "fail-0012-partial-success",
      "service.name": "api-gateway",
      "http.method": "GET",
      "http.route": "/api/v2/products/:id",
      "http.status_code": 200,
      "duration_ms": 89,
      "span_count": 5,
      "error": false,
      "incident.phase": "partial-availability",
      "note": "Product service unaffected by order-service outage",
      "timestamp_offset_seconds": 140
    },
    {
      "trace_id": "fail-0013-degraded-search",
      "service.name": "api-gateway",
      "http.method": "GET",
      "http.route": "/api/v2/search",
      "http.status_code": 206,
      "duration_ms": 234,
      "span_count": 8,
      "error": false,
      "incident.phase": "degraded-mode",
      "degraded.missing_features": ["order_history_boost", "purchase_recommendations"],
      "degraded.reason": "order-service unavailable",
      "timestamp_offset_seconds": 145
    },
    {
      "trace_id": "fail-0014-fallback-cache",
      "service.name": "api-gateway",
      "http.method": "GET",
      "http.route": "/api/v2/orders/:id",
      "http.status_code": 200,
      "duration_ms": 12,
      "span_count": 3,
      "error": false,
      "incident.phase": "fallback-active",
      "fallback.type": "stale-cache",
      "fallback.cache_age_seconds": 3600,
      "fallback.warning": "Data may be stale",
      "cache.hit": true,
      "timestamp_offset_seconds": 150
    },
    {
      "trace_id": "fail-0015-alert-triggered",
      "service.name": "monitoring-service",
      "http.method": "POST",
      "http.route": "/internal/alerts",
      "http.status_code": 200,
      "duration_ms": 45,
      "span_count": 4,
      "error": false,
      "incident.phase": "alerting",
      "alert.name": "order-service-high-error-rate",
      "alert.severity": "critical",
      "alert.channels": ["pagerduty", "slack"],
      "alert.error_rate_percent": 95.5,
      "timestamp_offset_seconds": 155
    },
    {
      "trace_id": "fail-0016-db-recovery-start",
      "service.name": "order-service",
      "db.system": "postgresql",
      "db.operation": "SELECT",
      "http.status_code": 200,
      "duration_ms": 450,
      "span_count": 3,
      "error": false,
      "incident.phase": "recovery-start",
      "db.connection_pool.active": 15,
      "db.connection_pool.max": 20,
      "db.connection_pool.waiting": 2,
      "note": "Database load decreasing",
      "timestamp_offset_seconds": 600
    },
    {
      "trace_id": "fail-0017-circuit-half-open",
      "service.name": "api-gateway",
      "http.method": "GET",
      "http.route": "/api/v2/orders/:id",
      "http.status_code": 200,
      "duration_ms": 890,
      "span_count": 6,
      "error": false,
      "incident.phase": "circuit-half-open",
      "circuit_breaker.state": "half-open",
      "circuit_breaker.test_request": true,
      "circuit_breaker.success_count": 1,
      "circuit_breaker.success_threshold": 5,
      "timestamp_offset_seconds": 660
    },
    {
      "trace_id": "fail-0018-circuit-testing",
      "service.name": "api-gateway",
      "http.method": "GET",
      "http.route": "/api/v2/orders/:id",
      "http.status_code": 200,
      "duration_ms": 234,
      "span_count": 6,
      "error": false,
      "incident.phase": "circuit-half-open",
      "circuit_breaker.state": "half-open",
      "circuit_breaker.success_count": 3,
      "circuit_breaker.success_threshold": 5,
      "timestamp_offset_seconds": 680
    },
    {
      "trace_id": "fail-0019-circuit-closed",
      "service.name": "api-gateway",
      "http.method": "GET",
      "http.route": "/api/v2/orders/:id",
      "http.status_code": 200,
      "duration_ms": 67,
      "span_count": 6,
      "error": false,
      "incident.phase": "circuit-closed",
      "circuit_breaker.state": "closed",
      "circuit_breaker.success_count": 5,
      "circuit_breaker.reset": true,
      "timestamp_offset_seconds": 720
    },
    {
      "trace_id": "fail-0020-recovery-complete",
      "service.name": "api-gateway",
      "http.method": "GET",
      "http.route": "/api/v2/orders/:id",
      "http.status_code": 200,
      "duration_ms": 45,
      "span_count": 6,
      "error": false,
      "incident.phase": "recovered",
      "db.connection_pool.active": 8,
      "db.connection_pool.max": 20,
      "db.connection_pool.waiting": 0,
      "timestamp_offset_seconds": 900
    },
    {
      "trace_id": "fail-0021-thundering-herd",
      "service.name": "cache-service",
      "http.method": "GET",
      "http.route": "/internal/cache/:key",
      "http.status_code": 200,
      "duration_ms": 2345,
      "span_count": 15,
      "error": false,
      "incident.phase": "thundering-herd",
      "cache.miss": true,
      "cache.concurrent_fetches": 150,
      "cache.key": "popular-products-list",
      "cache.stampede_protection": false,
      "timestamp_offset_seconds": 950
    },
    {
      "trace_id": "fail-0022-stampede-mitigated",
      "service.name": "cache-service",
      "http.method": "GET",
      "http.route": "/internal/cache/:key",
      "http.status_code": 200,
      "duration_ms": 45,
      "span_count": 3,
      "error": false,
      "incident.phase": "stampede-protected",
      "cache.miss": true,
      "cache.singleflight": true,
      "cache.coalesced_requests": 149,
      "cache.key": "popular-products-list",
      "timestamp_offset_seconds": 960
    },
    {
      "trace_id": "fail-0023-rate-limit-429",
      "service.name": "api-gateway",
      "http.method": "GET",
      "http.route": "/api/v2/products",
      "http.status_code": 429,
      "duration_ms": 3,
      "span_count": 2,
      "error": true,
      "error.message": "Rate limit exceeded",
      "incident.phase": "rate-limiting",
      "rate_limit.bucket": "api-read",
      "rate_limit.limit": 1000,
      "rate_limit.remaining": 0,
      "rate_limit.reset_seconds": 45,
      "rate_limit.retry_after": 45,
      "timestamp_offset_seconds": 200
    },
    {
      "trace_id": "fail-0024-load-shed",
      "service.name": "api-gateway",
      "http.method": "POST",
      "http.route": "/api/v2/orders",
      "http.status_code": 503,
      "duration_ms": 5,
      "span_count": 2,
      "error": true,
      "error.message": "Service overloaded - shedding load",
      "incident.phase": "load-shedding",
      "load_shed.queue_depth": 5000,
      "load_shed.threshold": 1000,
      "load_shed.priority": "low",
      "timestamp_offset_seconds": 180
    },
    {
      "trace_id": "fail-0025-priority-preserved",
      "service.name": "api-gateway",
      "http.method": "POST",
      "http.route": "/api/v2/checkout/complete",
      "http.status_code": 200,
      "duration_ms": 1234,
      "span_count": 25,
      "error": false,
      "incident.phase": "load-shedding",
      "load_shed.priority": "critical",
      "load_shed.preserved": true,
      "note": "High-priority checkout preserved during load shed",
      "timestamp_offset_seconds": 185
    },
    {
      "trace_id": "fail-0026-timeout-cascade-l1",
      "service.name": "api-gateway",
      "http.method": "GET",
      "http.route": "/api/v2/dashboard",
      "http.status_code": 504,
      "duration_ms": 10000,
      "span_count": 3,
      "error": true,
      "error.message": "Gateway timeout",
      "incident.phase": "timeout-cascade",
      "timeout.configured_ms": 10000,
      "timeout.layer": "gateway",
      "timestamp_offset_seconds": 250
    },
    {
      "trace_id": "fail-0027-timeout-cascade-l2",
      "service.name": "dashboard-service",
      "http.method": "GET",
      "http.route": "/internal/aggregate",
      "http.status_code": 504,
      "duration_ms": 9500,
      "span_count": 8,
      "error": true,
      "error.message": "Upstream timeout from analytics-service",
      "incident.phase": "timeout-cascade",
      "timeout.configured_ms": 8000,
      "timeout.layer": "service",
      "timeout.upstream": "analytics-service",
      "timestamp_offset_seconds": 250
    },
    {
      "trace_id": "fail-0028-timeout-cascade-l3",
      "service.name": "analytics-service",
      "http.method": "GET",
      "http.route": "/internal/metrics",
      "http.status_code": 504,
      "duration_ms": 8000,
      "span_count": 5,
      "error": true,
      "error.message": "Database query timeout",
      "incident.phase": "timeout-cascade",
      "timeout.configured_ms": 5000,
      "timeout.layer": "database",
      "db.query_duration_ms": 8000,
      "timestamp_offset_seconds": 250
    },
    {
      "trace_id": "fail-0029-memory-pressure",
      "service.name": "report-service",
      "http.method": "GET",
      "http.route": "/api/v2/reports/large",
      "http.status_code": 500,
      "duration_ms": 15000,
      "span_count": 12,
      "error": true,
      "error.message": "OutOfMemoryError: Java heap space",
      "incident.phase": "memory-pressure",
      "jvm.heap_used_bytes": 8053063680,
      "jvm.heap_max_bytes": 8589934592,
      "jvm.gc_pause_ms": 12000,
      "jvm.gc_type": "Full GC",
      "timestamp_offset_seconds": 300
    },
    {
      "trace_id": "fail-0030-graceful-degradation",
      "service.name": "api-gateway",
      "http.method": "GET",
      "http.route": "/api/v2/homepage",
      "http.status_code": 200,
      "duration_ms": 156,
      "span_count": 8,
      "error": false,
      "incident.phase": "graceful-degradation",
      "degraded.features_disabled": ["personalization", "recommendations", "recently_viewed"],
      "degraded.reason": "ml-service unavailable",
      "degraded.fallback": "static-content",
      "timestamp_offset_seconds": 400
    },
    {
      "trace_id": "fail-0031-partial-batch-failure",
      "service.name": "notification-service",
      "http.method": "POST",
      "http.route": "/internal/batch/send",
      "http.status_code": 207,
      "duration_ms": 5670,
      "span_count": 150,
      "error": false,
      "incident.phase": "partial-failure",
      "batch.total": 100,
      "batch.succeeded": 87,
      "batch.failed": 13,
      "batch.failure_reasons": {"invalid_email": 8, "rate_limited": 5},
      "timestamp_offset_seconds": 450
    },
    {
      "trace_id": "fail-0032-dns-failure",
      "service.name": "payment-service",
      "http.method": "POST",
      "http.route": "/internal/charge",
      "http.status_code": 503,
      "duration_ms": 5000,
      "span_count": 3,
      "error": true,
      "error.message": "DNS resolution failed: api.stripe.com",
      "incident.phase": "dns-failure",
      "dns.query": "api.stripe.com",
      "dns.error": "SERVFAIL",
      "dns.attempts": 3,
      "timestamp_offset_seconds": 500
    },
    {
      "trace_id": "fail-0033-tls-handshake",
      "service.name": "payment-service",
      "http.method": "POST",
      "http.route": "/internal/charge",
      "http.status_code": 503,
      "duration_ms": 30000,
      "span_count": 3,
      "error": true,
      "error.message": "TLS handshake timeout",
      "incident.phase": "tls-failure",
      "tls.version": "TLSv1.3",
      "tls.peer": "api.stripe.com:443",
      "tls.timeout_ms": 30000,
      "timestamp_offset_seconds": 510
    },
    {
      "trace_id": "fail-0034-cert-expiry",
      "service.name": "webhook-service",
      "http.method": "POST",
      "http.route": "/internal/deliver",
      "http.status_code": 503,
      "duration_ms": 234,
      "span_count": 3,
      "error": true,
      "error.message": "Certificate verification failed: certificate has expired",
      "incident.phase": "cert-expiry",
      "tls.cert_expiry": "2024-01-14T00:00:00Z",
      "tls.peer": "partner-webhook.example.com",
      "timestamp_offset_seconds": 520
    },
    {
      "trace_id": "fail-0035-connection-reset",
      "service.name": "api-gateway",
      "http.method": "GET",
      "http.route": "/api/v2/products",
      "http.status_code": 502,
      "duration_ms": 45,
      "span_count": 3,
      "error": true,
      "error.message": "Connection reset by peer",
      "incident.phase": "network-error",
      "tcp.error": "ECONNRESET",
      "tcp.peer": "10.0.45.67:8080",
      "timestamp_offset_seconds": 530
    },
    {
      "trace_id": "fail-0036-resource-exhaustion",
      "service.name": "api-gateway",
      "http.method": "POST",
      "http.route": "/api/v2/uploads",
      "http.status_code": 503,
      "duration_ms": 12,
      "span_count": 2,
      "error": true,
      "error.message": "Too many open files",
      "incident.phase": "fd-exhaustion",
      "os.open_files": 65535,
      "os.max_files": 65535,
      "timestamp_offset_seconds": 540
    },
    {
      "trace_id": "fail-0037-disk-full",
      "service.name": "log-aggregator",
      "http.method": "POST",
      "http.route": "/internal/ingest",
      "http.status_code": 507,
      "duration_ms": 5,
      "span_count": 2,
      "error": true,
      "error.message": "Insufficient storage: disk full",
      "incident.phase": "disk-exhaustion",
      "disk.used_bytes": 107374182400,
      "disk.total_bytes": 107374182400,
      "disk.mount": "/var/log",
      "timestamp_offset_seconds": 550
    },
    {
      "trace_id": "fail-0038-deadlock",
      "service.name": "inventory-service",
      "db.system": "postgresql",
      "db.operation": "UPDATE",
      "http.status_code": 500,
      "duration_ms": 30000,
      "span_count": 4,
      "error": true,
      "error.message": "ERROR: deadlock detected",
      "incident.phase": "database-deadlock",
      "db.deadlock.process_a": "UPDATE inventory SET quantity = quantity - 1 WHERE sku = 'ABC'",
      "db.deadlock.process_b": "UPDATE inventory SET quantity = quantity + 1 WHERE sku = 'XYZ'",
      "timestamp_offset_seconds": 560
    },
    {
      "trace_id": "fail-0039-lock-timeout",
      "service.name": "order-service",
      "db.system": "postgresql",
      "db.operation": "UPDATE",
      "http.status_code": 500,
      "duration_ms": 10000,
      "span_count": 3,
      "error": true,
      "error.message": "ERROR: lock wait timeout exceeded",
      "incident.phase": "lock-contention",
      "db.lock_wait_ms": 10000,
      "db.lock_type": "row exclusive",
      "db.blocked_by_pid": 12345,
      "timestamp_offset_seconds": 570
    },
    {
      "trace_id": "fail-0040-replication-lag",
      "service.name": "user-service",
      "db.system": "postgresql",
      "db.operation": "SELECT",
      "http.status_code": 200,
      "duration_ms": 12,
      "span_count": 3,
      "error": false,
      "incident.phase": "replication-lag",
      "db.replica": true,
      "db.replication_lag_bytes": 104857600,
      "db.replication_lag_seconds": 45,
      "warning": "Stale read - replication lag detected",
      "timestamp_offset_seconds": 580
    },
    {
      "trace_id": "fail-0041-queue-backlog",
      "service.name": "worker-service",
      "messaging.system": "rabbitmq",
      "messaging.operation": "receive",
      "http.status_code": 200,
      "duration_ms": 45,
      "span_count": 3,
      "error": false,
      "incident.phase": "queue-backlog",
      "queue.name": "order-processing",
      "queue.depth": 50000,
      "queue.normal_depth": 100,
      "queue.consumer_count": 5,
      "queue.message_age_seconds": 1800,
      "timestamp_offset_seconds": 590
    },
    {
      "trace_id": "fail-0042-poison-message",
      "service.name": "worker-service",
      "messaging.system": "rabbitmq",
      "messaging.operation": "receive",
      "http.status_code": 500,
      "duration_ms": 234,
      "span_count": 4,
      "error": true,
      "error.message": "Failed to deserialize message: invalid JSON",
      "incident.phase": "poison-message",
      "queue.name": "order-processing",
      "queue.delivery_count": 5,
      "queue.max_retries": 5,
      "queue.dead_letter": true,
      "timestamp_offset_seconds": 600
    },
    {
      "trace_id": "fail-0043-split-brain",
      "service.name": "leader-election",
      "http.method": "POST",
      "http.route": "/internal/heartbeat",
      "http.status_code": 409,
      "duration_ms": 45,
      "span_count": 3,
      "error": true,
      "error.message": "Split brain detected: multiple leaders",
      "incident.phase": "split-brain",
      "cluster.leaders": ["node-1", "node-3"],
      "cluster.expected_leader": 1,
      "cluster.partition_detected": true,
      "timestamp_offset_seconds": 610
    },
    {
      "trace_id": "fail-0044-config-drift",
      "service.name": "api-gateway",
      "http.method": "GET",
      "http.route": "/api/v2/products",
      "http.status_code": 500,
      "duration_ms": 5,
      "span_count": 2,
      "error": true,
      "error.message": "Configuration error: unknown route handler",
      "incident.phase": "config-drift",
      "config.version": "v2.3.4",
      "config.expected_version": "v2.3.5",
      "config.last_sync": "2024-01-15T10:00:00Z",
      "timestamp_offset_seconds": 620
    },
    {
      "trace_id": "fail-0045-version-mismatch",
      "service.name": "api-gateway",
      "http.method": "POST",
      "http.route": "/api/v2/orders",
      "http.status_code": 500,
      "duration_ms": 45,
      "span_count": 5,
      "error": true,
      "error.message": "Protocol version mismatch: expected v3, got v2",
      "incident.phase": "version-mismatch",
      "api.client_version": "2.0.0",
      "api.server_version": "3.0.0",
      "api.breaking_change": true,
      "timestamp_offset_seconds": 630
    },
    {
      "trace_id": "fail-0046-feature-flag-error",
      "service.name": "api-gateway",
      "http.method": "GET",
      "http.route": "/api/v2/checkout",
      "http.status_code": 500,
      "duration_ms": 1234,
      "span_count": 8,
      "error": true,
      "error.message": "Feature flag evaluation failed: LaunchDarkly timeout",
      "incident.phase": "feature-flag-failure",
      "feature_flag.provider": "launchdarkly",
      "feature_flag.timeout_ms": 1000,
      "feature_flag.fallback_used": false,
      "timestamp_offset_seconds": 640
    },
    {
      "trace_id": "fail-0047-feature-flag-fallback",
      "service.name": "api-gateway",
      "http.method": "GET",
      "http.route": "/api/v2/checkout",
      "http.status_code": 200,
      "duration_ms": 234,
      "span_count": 8,
      "error": false,
      "incident.phase": "feature-flag-fallback",
      "feature_flag.provider": "launchdarkly",
      "feature_flag.fallback_used": true,
      "feature_flag.fallback_value": "control",
      "timestamp_offset_seconds": 650
    },
    {
      "trace_id": "fail-0048-canary-failure",
      "service.name": "api-gateway",
      "http.method": "GET",
      "http.route": "/api/v2/products",
      "http.status_code": 500,
      "duration_ms": 67,
      "span_count": 4,
      "error": true,
      "error.message": "NullPointerException in ProductSerializer",
      "incident.phase": "canary-failure",
      "deployment.version": "v2.4.0-canary",
      "deployment.canary_percent": 5,
      "deployment.canary_instance": "api-gateway-canary-7d9f8",
      "timestamp_offset_seconds": 700
    },
    {
      "trace_id": "fail-0049-canary-rollback",
      "service.name": "deployment-controller",
      "http.method": "POST",
      "http.route": "/internal/rollback",
      "http.status_code": 200,
      "duration_ms": 5670,
      "span_count": 15,
      "error": false,
      "incident.phase": "canary-rollback",
      "deployment.from_version": "v2.4.0-canary",
      "deployment.to_version": "v2.3.5",
      "deployment.rollback_reason": "error_rate_exceeded",
      "deployment.error_rate_percent": 15.5,
      "deployment.error_rate_threshold": 5.0,
      "timestamp_offset_seconds": 710
    },
    {
      "trace_id": "fail-0050-post-incident-normal",
      "service.name": "api-gateway",
      "http.method": "GET",
      "http.route": "/api/v2/orders/:id",
      "http.status_code": 200,
      "duration_ms": 45,
      "span_count": 6,
      "error": false,
      "incident.phase": "post-incident",
      "note": "System fully recovered",
      "timestamp_offset_seconds": 900
    },
    {
      "trace_id": "fail-0051-chaos-monkey",
      "service.name": "inventory-service",
      "http.method": "GET",
      "http.route": "/internal/stock/:sku",
      "http.status_code": 500,
      "duration_ms": 5,
      "span_count": 2,
      "error": true,
      "error.message": "Chaos Monkey: artificial failure injected",
      "chaos.enabled": true,
      "chaos.failure_type": "exception",
      "chaos.probability": 0.01,
      "timestamp_offset_seconds": 1000
    },
    {
      "trace_id": "fail-0052-chaos-latency",
      "service.name": "product-service",
      "http.method": "GET",
      "http.route": "/internal/products/:id",
      "http.status_code": 200,
      "duration_ms": 5000,
      "span_count": 4,
      "error": false,
      "chaos.enabled": true,
      "chaos.failure_type": "latency",
      "chaos.injected_latency_ms": 4900,
      "chaos.probability": 0.05,
      "timestamp_offset_seconds": 1010
    },
    {
      "trace_id": "fail-0053-network-partition",
      "service.name": "consensus-service",
      "http.method": "POST",
      "http.route": "/internal/raft/append",
      "http.status_code": 503,
      "duration_ms": 5000,
      "span_count": 3,
      "error": true,
      "error.message": "Network partition: cannot reach quorum",
      "incident.phase": "network-partition",
      "raft.term": 45,
      "raft.leader": "node-1",
      "raft.reachable_nodes": 2,
      "raft.required_nodes": 3,
      "timestamp_offset_seconds": 1050
    },
    {
      "trace_id": "fail-0054-gc-pause",
      "service.name": "search-service",
      "http.method": "GET",
      "http.route": "/api/v2/search",
      "http.status_code": 200,
      "duration_ms": 2345,
      "span_count": 6,
      "error": false,
      "incident.phase": "gc-pause",
      "jvm.gc_pause_ms": 2100,
      "jvm.gc_type": "G1 Young Generation",
      "jvm.heap_before_gc_mb": 7500,
      "jvm.heap_after_gc_mb": 2100,
      "timestamp_offset_seconds": 1100
    },
    {
      "trace_id": "fail-0055-cold-start",
      "service.name": "lambda-processor",
      "faas.invoked_name": "process-image",
      "http.status_code": 200,
      "duration_ms": 8900,
      "span_count": 5,
      "error": false,
      "incident.phase": "cold-start",
      "faas.cold_start": true,
      "faas.init_duration_ms": 8500,
      "faas.execution_duration_ms": 400,
      "faas.memory_mb": 1024,
      "timestamp_offset_seconds": 1150
    },
    {
      "trace_id": "fail-0056-warm-invocation",
      "service.name": "lambda-processor",
      "faas.invoked_name": "process-image",
      "http.status_code": 200,
      "duration_ms": 450,
      "span_count": 4,
      "error": false,
      "incident.phase": "warm-invocation",
      "faas.cold_start": false,
      "faas.execution_duration_ms": 450,
      "faas.memory_mb": 1024,
      "timestamp_offset_seconds": 1160
    },
    {
      "trace_id": "fail-0057-bulkhead-reject",
      "service.name": "api-gateway",
      "http.method": "POST",
      "http.route": "/api/v2/reports/generate",
      "http.status_code": 503,
      "duration_ms": 5,
      "span_count": 2,
      "error": true,
      "error.message": "Bulkhead full: request rejected",
      "incident.phase": "bulkhead-rejection",
      "bulkhead.name": "report-generation",
      "bulkhead.max_concurrent": 10,
      "bulkhead.current": 10,
      "bulkhead.waiting": 25,
      "timestamp_offset_seconds": 1200
    },
    {
      "trace_id": "fail-0058-semaphore-timeout",
      "service.name": "batch-processor",
      "http.method": "POST",
      "http.route": "/internal/process",
      "http.status_code": 503,
      "duration_ms": 30000,
      "span_count": 3,
      "error": true,
      "error.message": "Semaphore acquisition timeout",
      "incident.phase": "semaphore-timeout",
      "semaphore.name": "db-connections",
      "semaphore.permits": 100,
      "semaphore.available": 0,
      "semaphore.timeout_ms": 30000,
      "timestamp_offset_seconds": 1250
    },
    {
      "trace_id": "fail-0059-backpressure",
      "service.name": "stream-processor",
      "messaging.system": "kafka",
      "messaging.operation": "receive",
      "http.status_code": 200,
      "duration_ms": 12,
      "span_count": 3,
      "error": false,
      "incident.phase": "backpressure",
      "stream.lag": 1000000,
      "stream.consumer_rate_per_sec": 5000,
      "stream.producer_rate_per_sec": 15000,
      "stream.backpressure_signal": true,
      "timestamp_offset_seconds": 1300
    },
    {
      "trace_id": "fail-0060-recovery-verified",
      "service.name": "monitoring-service",
      "http.method": "POST",
      "http.route": "/internal/verify-recovery",
      "http.status_code": 200,
      "duration_ms": 2345,
      "span_count": 25,
      "error": false,
      "incident.phase": "recovery-verified",
      "health.all_services_healthy": true,
      "health.error_rate_percent": 0.1,
      "health.latency_p99_ms": 89,
      "incident.duration_minutes": 15,
      "incident.id": "INC-2024-0115-001",
      "timestamp_offset_seconds": 1500
    }
  ]
}
